imdlib/__init__.py
imdlib/compute.py
imdlib/core.py
imdlib/naming.py
imdlib/real.py
imdlib/util.py
imdlib/version.py
imdlib-0.1.21.dist-info/licenses/LICENSE
imdlib-0.1.21.dist-info/METADATA
imdlib-0.1.21.dist-info/WHEEL
imdlib-0.1.21.dist-info/top_level.txt
imdlib-0.1.21.dist-info/RECORD
