Metadata-Version: 2.4
Name: imdlib
Version: 0.1.21
Summary: A tool for handling and downloading IMD gridded data
Home-page: https://github.com/iamsaswata/
Author: Saswata Nandi
Author-email: iamsaswata@yahoo.com
License: MIT
Keywords: imd,India,rainfall,data,hydrology,IMD,grid,grided,gridded
Classifier: Programming Language :: Python :: 3
Classifier: License :: OSI Approved :: MIT License
Classifier: Operating System :: OS Independent
Classifier: Development Status :: 4 - Beta
Classifier: Intended Audience :: Developers
Classifier: Intended Audience :: Science/Research
Classifier: License :: OSI Approved :: MIT License
Classifier: Operating System :: OS Independent
Classifier: Topic :: Scientific/Engineering :: Hydrology
Requires-Python: >=3.0
License-File: LICENSE
Requires-Dist: matplotlib
Requires-Dist: numpy
Requires-Dist: pandas
Requires-Dist: six
Requires-Dist: python-dateutil
Requires-Dist: pytz
Requires-Dist: urllib3
Requires-Dist: scipy
Requires-Dist: xarray
Requires-Dist: requests
Dynamic: author
Dynamic: author-email
Dynamic: classifier
Dynamic: description
Dynamic: description-content-type
Dynamic: home-page
Dynamic: keywords
Dynamic: license
Dynamic: license-file
Dynamic: requires-dist
Dynamic: requires-python
Dynamic: summary
